setup.py
FPE_SRWR/FPE_SRWR.py
FPE_SRWR/__init__.py
FPE_SRWR.egg-info/PKG-INFO
FPE_SRWR.egg-info/SOURCES.txt
FPE_SRWR.egg-info/dependency_links.txt
FPE_SRWR.egg-info/top_level.txt